nosedive-0.15.dist-info/metadata.json
nosedive-0.15.dist-info/entry_points.txt
nosedive-0.15.dist-info/METADATA
nosedive-0.15.dist-info/RECORD
nosedive-0.15.dist-info/top_level.txt
nosedive-0.15.dist-info/DESCRIPTION.rst
nosedive-0.15.dist-info/WHEEL
NoseDive/__init__.py
NoseDive/depth.py
