Metadata-Version: 2.0
Name: nosedive
Version: 0.15
Summary: Nosedive is a stack depth tracer for Nose
Home-page: https://github.com/mattboyer/
Author: Matt Boyer
Author-email: mboyer@sdf.org
License: BSD
Keywords: nosetests
Platform: UNKNOWN
Classifier: Development Status :: 2 - Pre-Alpha
Requires-Dist: nose
